html_converter/__init__.py
html_converter/html_converter.py
html_converter-1.0.0.dist-info/LICENSE
html_converter-1.0.0.dist-info/METADATA
html_converter-1.0.0.dist-info/WHEEL
html_converter-1.0.0.dist-info/top_level.txt
html_converter-1.0.0.dist-info/RECORD
