Metadata-Version: 2.1
Name: html-converter
Version: 1.0.0
Summary: HTML converter tool
Home-page: https://github.com/dinceraslancom/html_converter
Author: Dincer Aslan
Author-email: dinceraslan.com@gmail.com
License: UNKNOWN
Project-URL: Source, https://github.com/dinceraslancom/html_converter
Platform: UNKNOWN
Classifier: Programming Language :: Python :: 3
Classifier: License :: OSI Approved :: MIT License
Classifier: Operating System :: OS Independent
Requires-Python: >=3.3
License-File: LICENSE
Requires-Dist: html5lib
